{
  "session_id": "ai-decision-1759587483091",
  "timestamp": "2025-10-04T14:18:03.092Z",
  "processing_info": {
    "session_significance": "SYSTEM_VALIDATION",
    "conversation_type": "AI_TRIGGERED",
    "duration_minutes": 30
  },
  "environment": {
    "platform": "MacOS",
    "shell": "zsh 5.9",
    "directory": "/Users/leeuwen/Programming/create-ai-chat-context",
    "user": "Dennis van Leeuwen"
  },
  "conversation_dump": {
    "user_inputs": [],
    "ai_responses": [],
    "decisions": [
      {
        "decision": "Session completed successfully",
        "rationale": "All requested tasks were completed",
        "impact": "Progress made on project objectives"
      }
    ],
    "insights": [
      "Session boundary detected: significant work completed"
    ],
    "technical_work": [],
    "files_modified": [],
    "next_steps": [
      "Continue monitoring for next natural break"
    ]
  },
  "metadata": {
    "metrics": {
      "conversation_length": 1,
      "technical_commands": 0,
      "files_created": 0,
      "estimated_tokens": 1000
    },
    "tags": [
      "session-dump",
      "technical-work"
    ]
  }
}